{
  "data" :[
    {
      "src" : "../pic/pic03.jpg",
      "link" : "#",
      "text" : "爆品馆"
    },
    {
      "src" : "../pic/pic03.jpg",
      "link" : "#",
      "text" : "爆品馆"
    },
    {
      "src" : "../pic/pic03.jpg",
      "link" : "#",
      "text" : "爆品馆"
    },
    {
      "src" : "../pic/pic03.jpg",
      "link" : "#",
      "text" : "爆品馆"
    },
    {
      "src" : "../pic/pic03.jpg",
      "link" : "#",
      "text" : "爆品馆"
    },
    {
      "src" : "../pic/pic03.jpg",
      "link" : "#",
      "text" : "爆品馆"
    }
  ],
  "datacode": "0"
}
